{
  "type": "page",
  "props": {},
  "children": [
    {
      "type": "stack",
      "props": { "direction": "column", "background": "", "scale": "1" },
      "children": [
        {
          "type": "display",
          "props": {
            "stateName": "$Display",
            "background": "white",
            "scale": "1"
          },
          "children": []
        },
        {
          "type": "grid",
          "props": {
            "rows": "6",
            "columns": "10",
            "tags": ["$group"],
            "match": "sequence",
            "name": "grid",
            "background": "white",
            "scale": "5"
          },
          "children": []
        }
      ]
    },
    {
      "type": "modal dialog",
      "props": { "stateName": "$modalOpen" },
      "children": [
        {
          "type": "stack",
          "props": { "direction": "row", "background": "", "scale": "1" },
          "children": [
            {
              "type": "grid",
              "props": {
                "rows": 3,
                "columns": 3,
                "tags": ["$lastToken"],
                "match": "contains",
                "name": "conjugateGrid",
                "background": "white",
                "scale": "3"
              },
              "children": []
            },
            {
              "type": "button",
              "props": {
                "label": "Cancel",
                "name": "cancel",
                "background": "",
                "scale": "1"
              },
              "children": []
            }
          ]
        }
      ]
    },
    {
      "type": "speech",
      "props": {},
      "children": []
    }
  ]
}
